ViswamAuth/__init__.py
viswamauth-1.0.dist-info/licenses/LICENSE.txt
viswamauth-1.0.dist-info/METADATA
viswamauth-1.0.dist-info/WHEEL
viswamauth-1.0.dist-info/top_level.txt
viswamauth-1.0.dist-info/RECORD
