Metadata-Version: 2.4
Name: ViswamAuth
Version: 1.0
Summary: ViswamAuth is a lightweight Python module for user authentication, featuring secure sign-up, login, passcode verification, and Gmail-based password recovery. Designed for Windows console applications, it is ideal for small projects, prototypes, and educational use.
Author: Viswam Groups and Technologies
Author-email: viswamgroupstechnologies@gmail.com
License: MIT
Keywords: authorization,signin,login,password,viswam
Classifier: Development Status :: 5 - Production/Stable
Classifier: Intended Audience :: Education
Classifier: Intended Audience :: Developers
Classifier: Operating System :: Microsoft :: Windows
Classifier: License :: OSI Approved :: MIT License
Classifier: Programming Language :: Python :: 3
Classifier: Programming Language :: Python :: 3.6
Classifier: Programming Language :: Python :: 3.7
Classifier: Programming Language :: Python :: 3.8
Classifier: Programming Language :: Python :: 3.9
Classifier: Programming Language :: Python :: 3.10
Requires-Python: >=3.6
License-File: LICENSE.txt
Requires-Dist: google-auth-oauthlib
Requires-Dist: google-api-python-client
Dynamic: author
Dynamic: author-email
Dynamic: classifier
Dynamic: description
Dynamic: description-content-type
Dynamic: keywords
Dynamic: license
Dynamic: license-file
Dynamic: requires-dist
Dynamic: requires-python
Dynamic: summary
